{
  "items": [
    {
      "id": "5f6b28d3a27c1d88789591cf",
      "title": "Family 1 common",
      "body": "Food body content",
      "sortPosition": 0,
      "tags": [
        "families",
        "another-tag",
        "last-item",
        "test"
      ],
      "parentScenarioId": "5f69bf51a27c1c3b84fe6447"
    },
    {
      "id": "5f6b28f6a27c1d88789591d9",
      "title": "Manchester families 2 body",
      "body": "Test body",
      "sortPosition": 0,
      "tags": [
        "families",
        "food",
        "common"
      ],
      "parentScenarioId": "5f69bf51a27c1c3b84fe6448"
    },
    {
      "id": "5f6b295ca27c1d88789591ef",
      "title": "Manchester families with ps",
      "body": "Body common",
      "sortPosition": 0,
      "tags": [
        "families",
        "another-tag",
        "parent"
      ],
      "parentScenarioId": "5f69bf51a27c1c3b84fe6447"
    },
    {
      "id": "5f69eac6a27c1d8c7cd68a5c",
      "title": "Tasty food without ps",
      "body": "Test body fine scenario",
      "sortPosition": 0,
      "tags": [
        "families",
        "another-tag",
        "new-good",
        "last-item",
        "parent"
      ],
      "parentScenarioId": null
    },
    {
      "id": "5f69ea16a27c1d33b03aa8f1",
      "title": "Test Without PS Unique title",
      "body": "Without all test body",
      "sortPosition": 0,
      "tags": [
        "families"
      ],
      "parentScenarioId": null
    }
  ],
  "total": 5
}